transfer_entropy_hemispheric/__init__.py
transfer_entropy_hemispheric/transfer_entropy_hemispheric.py
transfer_entropy_hemispheric-0.1.0.dist-info/METADATA
transfer_entropy_hemispheric-0.1.0.dist-info/WHEEL
transfer_entropy_hemispheric-0.1.0.dist-info/top_level.txt
transfer_entropy_hemispheric-0.1.0.dist-info/RECORD
